tests/__init__.py
tests/test_config_handler.py
tests/test_diff_handler.py
tests/test_git_handler.py
tests/test_gitlab_handler.py
diffrewind-0.3.1.dist-info/METADATA
diffrewind-0.3.1.dist-info/WHEEL
diffrewind-0.3.1.dist-info/entry_points.txt
diffrewind-0.3.1.dist-info/top_level.txt
diffrewind-0.3.1.dist-info/RECORD
