Metadata-Version: 2.1
Name: diffrewind
Version: 0.3.1
Requires-Dist: requests >=2.26.0
Provides-Extra: dev
Requires-Dist: pytest >=7.1.2 ; extra == 'dev'
